clear.py
pylotl.py
pylotl-0.0.40.dist-info/METADATA
pylotl-0.0.40.dist-info/WHEEL
pylotl-0.0.40.dist-info/top_level.txt
pylotl-0.0.40.dist-info/RECORD
