Metadata-Version: 2.4
Name: pylotl
Version: 0.0.40
Summary: pylotl is a web crawler!
Author: Invizabel
Project-URL: Homepage, https://github.com/Invizabel/pylotl
Project-URL: Bug Tracker, https://github.com/Invizabel/pylotl/issues
Classifier: Programming Language :: Python :: 3
Classifier: License :: OSI Approved :: MIT License
Classifier: Operating System :: OS Independent
Requires-Python: >=3.7
